LICENSE.md
README.md
setup.cfg
setup.py
traffic_light_classifier/__init__.py
traffic_light_classifier/datasets.py
traffic_light_classifier/extract_feature.py
traffic_light_classifier/helpers.py
traffic_light_classifier/model.py
traffic_light_classifier/modify_images.py
traffic_light_classifier/plots.py
traffic_light_classifier/statistics.py
traffic_light_classifier/tests.py
traffic_light_classifier.egg-info/PKG-INFO
traffic_light_classifier.egg-info/SOURCES.txt
traffic_light_classifier.egg-info/dependency_links.txt
traffic_light_classifier.egg-info/requires.txt
traffic_light_classifier.egg-info/top_level.txt
traffic_light_classifier/__auxil_subpkg__/__init__.py
traffic_light_classifier/__auxil_subpkg__/_auxil_submod.py
traffic_light_classifier/__auxil_subpkg__/images/all_lights.png
traffic_light_classifier/__auxil_subpkg__/images/feature_ext_steps.png
traffic_light_classifier/__auxil_subpkg__/images/masked_images.png
traffic_light_classifier/__auxil_subpkg__/images/processing_steps.png
traffic_light_classifier/__constants_subpkg__/__init__.py
traffic_light_classifier/__constants_subpkg__/_constants_submod.py
traffic_light_classifier/__constants_subpkg__/model_probabilistic.md
traffic_light_classifier/__data_subpkg__/__init__.py
traffic_light_classifier/__data_subpkg__/_data_submod.py
traffic_light_classifier/__data_subpkg__/dataset_test/green/00febbe1-a9ae-4b5f-b682-8ebfdae485a3.jpg
traffic_light_classifier/__data_subpkg__/dataset_test/green/01ae3c3d-21c8-4711-853a-ba6fda9553bf.jpg
traffic_light_classifier/__data_subpkg__/dataset_test/green/06ab17cd-888e-45de-9482-b432e23cea6a.jpg
traffic_light_classifier/__data_subpkg__/dataset_test/green/0a251f2f-babd-4257-87be-2940bd4bacc8.jpg
traffic_light_classifier/__data_subpkg__/dataset_test/green/0ab8c5a1-a750-4137-ad0a-13e5da55bd09.jpg
traffic_light_classifier/__data_subpkg__/dataset_test/green/0acf7bce-03d1-46af-aac2-bbca22e1c1cb.jpg
traffic_light_classifier/__data_subpkg__/dataset_test/green/0ae63733-c453-42b2-89cf-e4a7877feda6.jpg
traffic_light_classifier/__data_subpkg__/dataset_test/green/0aec12bd-ce95-4400-937b-ece1fd7c3011.jpg
traffic_light_classifier/__data_subpkg__/dataset_test/green/0b2b43f5-cad6-41a3-80ab-baf02e9f7ff1.jpg
