Metadata-Version: 2.1
Name: traffic-light-classifier
Version: 1.0.2
Summary: A computer vision & probabilistic approach based traffic light classifier.
Home-page: https://github.com/ShashankKumbhare/traffic-light-classifier
Author: Shashank Kumbhare
Author-email: shashankkumbhare8@gmail.com
License: MIT
Keywords: python,opencv,computer vision,ML,machine learning,traffic-light-classifier,self driving cars,AI,artificial intelligence
Platform: UNKNOWN
Classifier: License :: OSI Approved :: MIT License
Classifier: Natural Language :: English
Classifier: Operating System :: OS Independent
Classifier: Programming Language :: Python :: 3
License-File: LICENSE.md
